floryhugginsternary/__init__.py
floryhugginsternary/chemeq2.py
floryhugginsternary/chemeq3.py
floryhugginsternary/spinodal.py
floryhugginsternary-0.0.0.dist-info/LICENSE
floryhugginsternary-0.0.0.dist-info/METADATA
floryhugginsternary-0.0.0.dist-info/WHEEL
floryhugginsternary-0.0.0.dist-info/top_level.txt
floryhugginsternary-0.0.0.dist-info/RECORD
