Metadata-Version: 2.1
Name: floryhugginsternary
Version: 0.0.0
Summary: package to find tie-lines, binodals and spinodals in a three-component mixture with flory-huggins free energy.
Home-page: https://github.com/samueljmcameron/floryhugginsternary
Author: Sam Cameron
Author-email: samuel.j.m.cameron@gmail.com
License: UNKNOWN
Platform: UNKNOWN
Classifier: Programming Language :: Python :: 3
Classifier: License :: OSI Approved :: GNU General Public License v3 (GPLv3)
Classifier: Operating System :: OS Independent
Requires-Python: >=3.3
Requires-Dist: matplotlib (>=3)
Requires-Dist: numpy
